{"archived":false,"author":"iLykeVidyaGames","author_flair_css_class":"Armored","author_flair_text":"Text","brand_safe":true,"contest_mode":false,"created_utc":1504224153,"distinguished":null,"domain":"self.WWII","edited":false,"gilded":0,"hidden":false,"hide_score":false,"id":"6xavfm","is_crosspostable":false,"is_reddit_media_domain":false,"is_self":true,"is_video":false,"link_flair_css_class":"discussion","link_flair_text":"Discussion","locked":false,"media":null,"media_embed":{},"num_comments":12,"num_crossposts":0,"over_18":false,"parent_whitelist_status":"all_ads","permalink":"/r/WWII/comments/6xavfm/hk_method_not_working/","pinned":false,"retrieved_on":1507285934,"score":0,"secure_media":null,"secure_media_embed":{},"selftext":"[removed]","spoiler":false,"stickied":false,"subreddit":"WWII","subreddit_id":"t5_2r4qh","suggested_sort":"top","thumbnail":"default","thumbnail_height":null,"thumbnail_width":null,"title":"HK Method not working?","url":"https://www.reddit.com/r/WWII/comments/6xavfm/hk_method_not_working/","whitelist_status":"all_ads"}
