{"archived":false,"author":"[deleted]","author_flair_css_class":null,"author_flair_text":null,"brand_safe":true,"contest_mode":false,"created_utc":1504224085,"distinguished":null,"domain":"self.guineapigs","edited":false,"gilded":0,"hidden":false,"hide_score":false,"id":"6xav8k","is_crosspostable":false,"is_reddit_media_domain":false,"is_self":true,"is_video":false,"link_flair_css_class":null,"link_flair_text":null,"locked":false,"media":null,"media_embed":{},"num_comments":0,"num_crossposts":0,"over_18":false,"parent_whitelist_status":"all_ads","permalink":"/r/guineapigs/comments/6xav8k/my_piggy_has_some_dry_skin_in_his_ear_does_anyone/","pinned":false,"retrieved_on":1507285929,"score":2,"secure_media":null,"secure_media_embed":{},"selftext":"[deleted]","spoiler":false,"stickied":false,"subreddit":"guineapigs","subreddit_id":"t5_2rqn4","suggested_sort":null,"thumbnail":"default","thumbnail_height":null,"thumbnail_width":null,"title":"My piggy has some dry skin in his ear does anyone one know why ?","url":"https://www.reddit.com/r/guineapigs/comments/6xav8k/my_piggy_has_some_dry_skin_in_his_ear_does_anyone/","whitelist_status":"all_ads"}
