{"archived":false,"author":"frostfiree","author_flair_css_class":null,"author_flair_text":null,"brand_safe":false,"contest_mode":false,"created_utc":1504224192,"distinguished":null,"domain":"self.Phanteks","edited":false,"gilded":0,"hidden":false,"hide_score":false,"id":"6xavkn","is_crosspostable":false,"is_reddit_media_domain":false,"is_self":true,"is_video":false,"link_flair_css_class":null,"link_flair_text":null,"locked":false,"media":null,"media_embed":{},"num_comments":3,"num_crossposts":0,"over_18":false,"parent_whitelist_status":null,"permalink":"/r/Phanteks/comments/6xavkn/can_rgb_halos_be_used_without_connecting_to/","pinned":false,"retrieved_on":1507285937,"score":1,"secure_media":null,"secure_media_embed":{},"selftext":"I was wondering if you can use the RGB Halos fan LEDs without plugging them into motherboard and plugging them into the Phanteks Enthoo Evolv LED control instead. My motherboard doesn't have the RGB headers, since it was an older Z170 board. ","spoiler":false,"stickied":false,"subreddit":"Phanteks","subreddit_id":"t5_32l2t","suggested_sort":null,"thumbnail":"self","thumbnail_height":null,"thumbnail_width":null,"title":"can RGB halos be used without connecting to Motherboard?","url":"https://www.reddit.com/r/Phanteks/comments/6xavkn/can_rgb_halos_be_used_without_connecting_to/","whitelist_status":null}
