{"archived":false,"author":"unatasamra","author_flair_css_class":null,"author_flair_text":null,"brand_safe":false,"contest_mode":false,"created_utc":1504224129,"distinguished":null,"domain":"self.Luuk","edited":false,"gilded":0,"hidden":false,"hide_score":false,"id":"6xavd4","is_crosspostable":false,"is_reddit_media_domain":false,"is_self":true,"is_video":false,"link_flair_css_class":null,"link_flair_text":null,"locked":false,"media":null,"media_embed":{},"num_comments":0,"num_crossposts":0,"over_18":false,"parent_whitelist_status":null,"permalink":"/r/Luuk/comments/6xavd4/running_in_the_family_writer_michael_ondaatje/","pinned":false,"retrieved_on":1507285932,"score":1,"secure_media":null,"secure_media_embed":{},"selftext":"up7nm","spoiler":false,"stickied":false,"subreddit":"Luuk","subreddit_id":"t5_2wp7k","suggested_sort":null,"thumbnail":"self","thumbnail_height":null,"thumbnail_width":null,"title":"Running In The Family (writer Michael Ondaatje)","url":"https://www.reddit.com/r/Luuk/comments/6xavd4/running_in_the_family_writer_michael_ondaatje/","whitelist_status":null}
